src/__init__.py
src/timer_bot.py
timer_bot-1.10.dist-info/licenses/LICENSE
timer_bot-1.10.dist-info/METADATA
timer_bot-1.10.dist-info/WHEEL
timer_bot-1.10.dist-info/entry_points.txt
timer_bot-1.10.dist-info/top_level.txt
timer_bot-1.10.dist-info/RECORD
