Metadata-Version: 2.4
Name: timer-bot
Version: 1.10
Summary: Discord Timer Bot
Author-email: Lionel Panhaleux <lionel.panhaleux+timer@gmail.com>
Project-URL: Repository, https://github.com/lionel-panhaleux/timer-bot
Keywords: Discord,timer
Classifier: Programming Language :: Python :: 3
Classifier: Programming Language :: Python :: 3.11
Classifier: License :: OSI Approved :: MIT License
Classifier: Development Status :: 5 - Production/Stable
Classifier: Intended Audience :: Other Audience
Classifier: Natural Language :: English
Classifier: Operating System :: OS Independent
Classifier: Environment :: Web Environment
Requires-Python: >=3.11
License-File: LICENSE
Requires-Dist: discord-py-interactions>=5.14
Requires-Dist: uvloop>=0.21
Provides-Extra: dev
Requires-Dist: black; extra == "dev"
Requires-Dist: ruff; extra == "dev"
Requires-Dist: zest.releaser[recommended]; extra == "dev"
Dynamic: license-file
